rqd/__init__.py
rqd/__main__.py
rqd/cuerqd.py
rqd/rqconstants.py
rqd/rqcore.py
rqd/rqdocker.py
rqd/rqdservicers.py
rqd/rqexceptions.py
rqd/rqlogging.py
rqd/rqmachine.py
rqd/rqnetwork.py
rqd/rqnimby.py
rqd/rqswap.py
rqd/rqutil.py
opencue_rqd-1.13.8.dist-info/METADATA
opencue_rqd-1.13.8.dist-info/WHEEL
opencue_rqd-1.13.8.dist-info/entry_points.txt
opencue_rqd-1.13.8.dist-info/RECORD
