Metadata-Version: 2.1
Name: opencue_rqd
Version: 1.13.8
Summary: RQD is a software client that runs on all hosts doing work for an OpenCue deployment.
Requires-Python: >3.7
Requires-Dist: future==1.0.0
Requires-Dist: opencue-proto
Requires-Dist: psutil==5.9.8
Requires-Dist: pynput==1.7.6
Provides-Extra: test
Requires-Dist: docker==7.1.0; extra == 'test'
Requires-Dist: loki-urllib3-client; extra == 'test'
Requires-Dist: mock==2.0.0; extra == 'test'
Requires-Dist: pyfakefs==5.2.3; extra == 'test'
Requires-Dist: pytest; extra == 'test'
